odoo8_addon_account_payment_sale_stock-8.0.1.0.0.99.dev9-py2.7-nspkg.pth
odoo8_addon_account_payment_sale_stock-8.0.1.0.0.99.dev9.dist-info/DESCRIPTION.rst
odoo8_addon_account_payment_sale_stock-8.0.1.0.0.99.dev9.dist-info/METADATA
odoo8_addon_account_payment_sale_stock-8.0.1.0.0.99.dev9.dist-info/RECORD
odoo8_addon_account_payment_sale_stock-8.0.1.0.0.99.dev9.dist-info/WHEEL
odoo8_addon_account_payment_sale_stock-8.0.1.0.0.99.dev9.dist-info/metadata.json
odoo8_addon_account_payment_sale_stock-8.0.1.0.0.99.dev9.dist-info/namespace_packages.txt
odoo8_addon_account_payment_sale_stock-8.0.1.0.0.99.dev9.dist-info/top_level.txt
odoo_addons/account_payment_sale_stock/README.rst
odoo_addons/account_payment_sale_stock/__init__.py
odoo_addons/account_payment_sale_stock/__openerp__.py
odoo_addons/account_payment_sale_stock/i18n/account_payment_sale_stock.pot
odoo_addons/account_payment_sale_stock/i18n/de.po
odoo_addons/account_payment_sale_stock/i18n/es.po
odoo_addons/account_payment_sale_stock/i18n/es_AR.po
odoo_addons/account_payment_sale_stock/i18n/fi.po
odoo_addons/account_payment_sale_stock/i18n/fr.po
odoo_addons/account_payment_sale_stock/i18n/it.po
odoo_addons/account_payment_sale_stock/i18n/nl.po
odoo_addons/account_payment_sale_stock/i18n/pt_BR.po
odoo_addons/account_payment_sale_stock/i18n/sl.po
odoo_addons/account_payment_sale_stock/i18n/tr.po
odoo_addons/account_payment_sale_stock/i18n/tr_TR.po
odoo_addons/account_payment_sale_stock/models/__init__.py
odoo_addons/account_payment_sale_stock/models/stock_picking.py
odoo_addons/account_payment_sale_stock/static/description/icon.png
